<annotation>
	<folder>3</folder>
	<filename>145.jpg</filename>
	<path>C:\Users\14590\Desktop\1\3\145.jpg</path>
	<source>
		<database>Unknown</database>
	</source>
	<size>
		<width>1140</width>
		<height>640</height>
		<depth>3</depth>
	</size>
	<segmented>0</segmented>
	<object>
		<name>3</name>
		<pose>Unspecified</pose>
		<truncated>1</truncated>
		<difficult>0</difficult>
		<bndbox>
			<xmin>428</xmin>
			<ymin>92</ymin>
			<xmax>794</xmax>
			<ymax>640</ymax>
		</bndbox>
	</object>
</annotation>
