<annotation>
	<folder>19</folder>
	<filename>784.jpg</filename>
	<path>C:\Users\14590\Desktop\1\19\784.jpg</path>
	<source>
		<database>Unknown</database>
	</source>
	<size>
		<width>600</width>
		<height>335</height>
		<depth>3</depth>
	</size>
	<segmented>0</segmented>
	<object>
		<name>19</name>
		<pose>Unspecified</pose>
		<truncated>1</truncated>
		<difficult>0</difficult>
		<bndbox>
			<xmin>300</xmin>
			<ymin>1</ymin>
			<xmax>600</xmax>
			<ymax>199</ymax>
		</bndbox>
	</object>
	<object>
		<name>18</name>
		<pose>Unspecified</pose>
		<truncated>1</truncated>
		<difficult>0</difficult>
		<bndbox>
			<xmin>402</xmin>
			<ymin>201</ymin>
			<xmax>600</xmax>
			<ymax>333</ymax>
		</bndbox>
	</object>
	<object>
		<name>20</name>
		<pose>Unspecified</pose>
		<truncated>0</truncated>
		<difficult>0</difficult>
		<bndbox>
			<xmin>203</xmin>
			<ymin>202</ymin>
			<xmax>402</xmax>
			<ymax>334</ymax>
		</bndbox>
	</object>
	<object>
		<name>16</name>
		<pose>Unspecified</pose>
		<truncated>1</truncated>
		<difficult>0</difficult>
		<bndbox>
			<xmin>1</xmin>
			<ymin>1</ymin>
			<xmax>299</xmax>
			<ymax>199</ymax>
		</bndbox>
	</object>
</annotation>
