<annotation>
	<folder>21</folder>
	<filename>861.jpg</filename>
	<path>C:\Users\14590\Desktop\1\21\861.jpg</path>
	<source>
		<database>Unknown</database>
	</source>
	<size>
		<width>540</width>
		<height>358</height>
		<depth>3</depth>
	</size>
	<segmented>0</segmented>
	<object>
		<name>21</name>
		<pose>Unspecified</pose>
		<truncated>0</truncated>
		<difficult>0</difficult>
		<bndbox>
			<xmin>314</xmin>
			<ymin>7</ymin>
			<xmax>489</xmax>
			<ymax>134</ymax>
		</bndbox>
	</object>
</annotation>
